pyyso/__init__.py
pyyso/codec/__init__.py
pyyso/codec/aes.py
pyyso/misc/Lease.py
pyyso/misc/ReferenceWrapper_Stub.py
pyyso/misc/__init__.py
pyyso/server/__init__.py
pyyso/server/jrmp.py
pyyso/server/ldap.py
pyyso/server/mysql.py
pyyso/server/rmi.py
pyyso/yso/__init__.py
pyyso/yso/beanfactory.py
pyyso/yso/cb1v183.py
pyyso/yso/cb1v192.py
pyyso/yso/cc1.py
pyyso/yso/cc2.py
pyyso/yso/cc3.py
pyyso/yso/cc4.py
pyyso/yso/cc5.py
pyyso/yso/cc6.py
pyyso/yso/cc7.py
pyyso/yso/clazz.py
pyyso/yso/jdk7u21.py
pyyso/yso/jdk8u20.py
pyyso/yso/jrmpclient.py
pyyso/yso/urldns.py
pyyso-0.0.11.dist-info/LICENSE
pyyso-0.0.11.dist-info/METADATA
pyyso-0.0.11.dist-info/WHEEL
pyyso-0.0.11.dist-info/top_level.txt
pyyso-0.0.11.dist-info/RECORD
