Metadata-Version: 2.1
Name: pyyso
Version: 0.0.11
Summary: a java serialized tool written in python
Home-page: https://github.com/pypa/sampleproject
Author: greyclick
Author-email: cokeBeer@github.com
Project-URL: Bug Tracker, https://github.com/cokeBeer/pyyso/issues
Classifier: Programming Language :: Python :: 3
Classifier: License :: OSI Approved :: MIT License
Classifier: Operating System :: OS Independent
Requires-Python: >=3.6
License-File: LICENSE
Requires-Dist: pycrypto
